Ret2GPT/__init__.py
Ret2GPT/main.py
Ret2GPT/Ret2GPT/__init__.py
Ret2GPT/Ret2GPT/check_for_command.py
Ret2GPT/Ret2GPT/command_line.py
Ret2GPT/Ret2GPT/decompile.py
Ret2GPT/Ret2GPT/prompt_builder.py
Ret2GPT-1.0.3.dist-info/METADATA
Ret2GPT-1.0.3.dist-info/WHEEL
Ret2GPT-1.0.3.dist-info/entry_points.txt
Ret2GPT-1.0.3.dist-info/top_level.txt
Ret2GPT-1.0.3.dist-info/RECORD
